Workbook

Sheet Summary
A1: Enterprise Order-to-Cash - Manual Test Case Tracker
A3: Sanitized manual QA suite using the provided execution template for a configurable order-to-cash platform.
A5: Workbook Controls
A6: Default Status | B6: Not Run
A7: Default Priority | B7: Risk-based
A8: Portfolio Owner | B8: Candidate Portfolio
A9: Primary Domain | B9: Enterprise SaaS / Order-to-Cash QA
A11: Module Coverage
A12: Module | B12: Sheet Name | C12: Total Cases | D12: High Priority | E12: Negative Cases | F12: Automation Candidates
A13: System Setup & Admin | B13: Setup_Admin | C13: =COUNTA(Setup_Admin!A5:A200) -> 10 | D13: =COUNTIF(Setup_Admin!H:H,"High")+COUNTIF(Setup_Admin!H:H,"Critical") -> 8 | E13: =COUNTIF(Setup_Admin!I:I,"Negative")+COUNTIF(Setup_Admin!I:I,"Security")+COUNTIF(Setup_Admin!I:I,"Data") -> 5 | F13: =COUNTIF(Setup_Admin!J:J,"Yes") -> 5
A14: Customers & CRM | B14: Customers_CRM | C14: =COUNTA(Customers_CRM!A5:A200) -> 10 | D14: =COUNTIF(Customers_CRM!H:H,"High")+COUNTIF(Customers_CRM!H:H,"Critical") -> 7 | E14: =COUNTIF(Customers_CRM!I:I,"Negative")+COUNTIF(Customers_CRM!I:I,"Security")+COUNTIF(Customers_CRM!I:I,"Data") -> 4 | F14: =COUNTIF(Customers_CRM!J:J,"Yes") -> 5
A15: Sales & Orders | B15: Sales_Orders | C15: =COUNTA(Sales_Orders!A5:A200) -> 12 | D15: =COUNTIF(Sales_Orders!H:H,"High")+COUNTIF(Sales_Orders!H:H,"Critical") -> 10 | E15: =COUNTIF(Sales_Orders!I:I,"Negative")+COUNTIF(Sales_Orders!I:I,"Security")+COUNTIF(Sales_Orders!I:I,"Data") -> 3 | F15: =COUNTIF(Sales_Orders!J:J,"Yes") -> 7
A16: Components & Pricing | B16: Components_Pricing | C16: =COUNTA(Components_Pricing!A5:A200) -> 9 | D16: =COUNTIF(Components_Pricing!H:H,"High")+COUNTIF(Components_Pricing!H:H,"Critical") -> 8 | E16: =COUNTIF(Components_Pricing!I:I,"Negative")+COUNTIF(Components_Pricing!I:I,"Security")+COUNTIF(Components_Pricing!I:I,"Data") -> 1 | F16: =COUNTIF(Components_Pricing!J:J,"Yes") -> 3
A17: Financial Setup | B17: Financial_Config | C17: =COUNTA(Financial_Config!A5:A200) -> 10 | D17: =COUNTIF(Financial_Config!H:H,"High")+COUNTIF(Financial_Config!H:H,"Critical") -> 9 | E17: =COUNTIF(Financial_Config!I:I,"Negative")+COUNTIF(Financial_Config!I:I,"Security")+COUNTIF(Financial_Config!I:I,"Data") -> 4 | F17: =COUNTIF(Financial_Config!J:J,"Yes") -> 5
A18: Payments & Reconciliation | B18: Payments_Recon | C18: =COUNTA(Payments_Recon!A5:A200) -> 14 | D18: =COUNTIF(Payments_Recon!H:H,"High")+COUNTIF(Payments_Recon!H:H,"Critical") -> 14 | E18: =COUNTIF(Payments_Recon!I:I,"Negative")+COUNTIF(Payments_Recon!I:I,"Security")+COUNTIF(Payments_Recon!I:I,"Data") -> 3 | F18: =COUNTIF(Payments_Recon!J:J,"Yes") -> 8
A19: Integrations & Reporting | B19: Integrations_Reports | C19: =COUNTA(Integrations_Reports!A5:A200) -> 11 | D19: =COUNTIF(Integrations_Reports!H:H,"High")+COUNTIF(Integrations_Reports!H:H,"Critical") -> 10 | E19: =COUNTIF(Integrations_Reports!I:I,"Negative")+COUNTIF(Integrations_Reports!I:I,"Security")+COUNTIF(Integrations_Reports!I:I,"Data") -> 3 | F19: =COUNTIF(Integrations_Reports!J:J,"Yes") -> 4
A20: End-to-End | B20: End_to_End | C20: =COUNTA(End_to_End!A5:A200) -> 8 | D20: =COUNTIF(End_to_End!H:H,"High")+COUNTIF(End_to_End!H:H,"Critical") -> 8 | E20: =COUNTIF(End_to_End!I:I,"Negative")+COUNTIF(End_to_End!I:I,"Security")+COUNTIF(End_to_End!I:I,"Data") -> 3 | F20: =COUNTIF(End_to_End!J:J,"Yes") -> 1
A21: Total | C21: =SUM(C13:C20) -> 84 | D21: =SUM(D13:D20) -> 74 | E21: =SUM(E13:E20) -> 26 | F21: =SUM(F13:F20) -> 38
A22: Execution Status
A23: Status | B23: Count | D23: Execution KPI
A24: Not Run | B24: =COUNTIF(Setup_Admin!K:K,A24)+COUNTIF(Customers_CRM!K:K,A24)+COUNTIF(Sales_Orders!K:K,A24)+COUNTIF(Components_Pricing!K:K,A24)+COUNTIF(Financial_Config!K:K,A24)+COUNTIF(Payments_Recon!K:K,A24)+COUNTIF(Integrations_Reports!K:K,A24)+COUNTIF(End_to_End!K:K,A24) -> 84 | D24: Total Test Cases | E24: =SUM(B24:B27) -> 84
A25: Pass | B25: =COUNTIF(Setup_Admin!K:K,A25)+COUNTIF(Customers_CRM!K:K,A25)+COUNTIF(Sales_Orders!K:K,A25)+COUNTIF(Components_Pricing!K:K,A25)+COUNTIF(Financial_Config!K:K,A25)+COUNTIF(Payments_Recon!K:K,A25)+COUNTIF(Integrations_Reports!K:K,A25)+COUNTIF(End_to_End!K:K,A25) -> 0 | D25: Executed Cases | E25: =B25+B26+B27 -> 0
A26: Fail | B26: =COUNTIF(Setup_Admin!K:K,A26)+COUNTIF(Customers_CRM!K:K,A26)+COUNTIF(Sales_Orders!K:K,A26)+COUNTIF(Components_Pricing!K:K,A26)+COUNTIF(Financial_Config!K:K,A26)+COUNTIF(Payments_Recon!K:K,A26)+COUNTIF(Integrations_Reports!K:K,A26)+COUNTIF(End_to_End!K:K,A26) -> 0 | D26: Pass Rate | E26: =IF(E25=0,0,B25/E25) -> 0
A27: Blocked | B27: =COUNTIF(Setup_Admin!K:K,A27)+COUNTIF(Customers_CRM!K:K,A27)+COUNTIF(Sales_Orders!K:K,A27)+COUNTIF(Components_Pricing!K:K,A27)+COUNTIF(Financial_Config!K:K,A27)+COUNTIF(Payments_Recon!K:K,A27)+COUNTIF(Integrations_Reports!K:K,A27)+COUNTIF(End_to_End!K:K,A27) -> 0 | D27: Fail Rate | E27: =IF(E25=0,0,B26/E25) -> 0

Sheet Setup_Admin
A1: System Setup and Administration Test Cases
A2: Update the Status column during execution. Summary KPIs and counts refresh automatically.
A4: TC_ID | B4: Module | C4: Scenario | D4: Preconditions | E4: Steps | F4: Test Data | G4: Expected Result | H4: Priority | I4: Type | J4: Automation Candidate | K4: Status | L4: Notes
A5: TC-SET-001 | B5: System Setup & Admin | C5: Verify a new location can be created with required details | D5: Admin user has access to setup | E5: 1. Open Location Settings 2. Create a new location with required name, address, and timezone 3. Save the record | F5: Valid location master data | G5: Location saves successfully and appears in location lists and selectors | H5: High | I5: Positive | J5: Yes | K5: Not Run | L5: Req: SETUP-LOC-001 | Risk: location master data integrity
A6: TC-SET-002 | B6: System Setup & Admin | C6: Verify duplicate location code or name is rejected | D6: Location with same code already exists | E6: 1. Open Location Settings 2. Enter a duplicate location code or duplicate unique name 3. Save the record | F6: Existing location code/name | G6: Validation prevents duplicate setup and no second location is created | H6: High | I6: Negative | J6: Yes | K6: Not Run | L6: Req: SETUP-LOC-002 | Risk: duplicate posting location
A7: TC-SET-003 | B7: System Setup & Admin | C7: Verify email from-address setup rejects invalid sender format | D7: Email domain setup page is available | E7: 1. Open email sender settings 2. Enter an invalid from address format 3. Attempt to save | F7: Invalid sender address | G7: Invalid address is rejected with clear validation message | H7: Medium | I7: Negative | J7: Yes | K7: Not Run | L7: Req: SETUP-EMAIL-001 | Risk: failed customer notifications
A8: TC-SET-004 | B8: System Setup & Admin | C8: Verify role-based access blocks non-finance users from financial setup pages | D8: User without finance setup permission exists | E8: 1. Sign in as restricted user 2. Attempt to open financial setup pages 3. Attempt direct URL access if applicable | F8: Restricted user role | G8: Access is denied consistently and audit trail or error message is shown | H8: Critical | I8: Security | J8: Yes | K8: Not Run | L8: Req: ACCESS-001 | Risk: unauthorized configuration changes
A9: TC-SET-005 | B9: System Setup & Admin | C9: Verify permission changes take effect after user session refresh | D9: Employee account exists and role can be edited | E9: 1. Remove a permission from an active user 2. Refresh or re-login as that user 3. Attempt the previously allowed action | F9: Existing employee and updated role | G9: Updated permission model is enforced after refresh without stale access | H9: High | I9: Regression | J9: Later | K9: Not Run | L9: Req: ACCESS-002 | Risk: stale authorization cache
A10: TC-SET-006 | B10: System Setup & Admin | C10: Verify configured notification triggers send the correct template on order status change | D10: Notification rule exists for a target status | E10: 1. Create or update an order to the trigger status 2. Review outbound notification preview or log 3. Confirm only intended recipients are targeted | F10: Sample order and recipient | G10: Correct template, recipients, and merge fields are used once per event | H10: High | I10: Integration | J10: Later | K10: Not Run | L10: Req: NOTIFY-001 | Risk: duplicate or incorrect customer communications
A11: TC-SET-007 | B11: System Setup & Admin | C11: Verify automation rule executes only when configured criteria are met | D11: Automation rule is enabled with specific criteria | E11: 1. Create a record that matches the automation criteria 2. Verify automation action fires 3. Create a similar record that does not match 4. Verify no action fires | F11: Matching and non-matching records | G11: Automation runs only for eligible records and creates the configured result | H11: Critical | I11: Integration | J11: Later | K11: Not Run | L11: Req: AUTO-001 | Risk: unintended workflow changes
A12: TC-SET-008 | B12: System Setup & Admin | C12: Verify localization settings update currency and date display consistently | D12: Localization settings page is available | E12: 1. Change locale/currency/date format settings in QA 2. Open estimate, order, and report screens 3. Review displayed dates, separators, and currency symbols | F12: Sample transactions across modules | G12: Localized formats are applied consistently without changing stored values | H12: Medium | I12: Regression | J12: Later | K12: Not Run | L12: Req: LOCAL-001 | Risk: misleading financial presentation
A13: TC-SET-009 | B13: System Setup & Admin | C13: Verify inactive employee can no longer log in or be assigned to new work | D13: Active employee record exists | E13: 1. Deactivate an employee 2. Attempt sign-in 3. Create or edit an order and try assigning the inactive employee | F13: Inactive employee account | G13: Login is blocked and inactive employee is excluded from new assignments | H13: High | I13: Negative | J13: Yes | K13: Not Run | L13: Req: EMP-001 | Risk: inactive user activity
A14: TC-SET-010 | B14: System Setup & Admin | C14: Verify manager time-tracking visibility is limited to authorized team members | D14: Manager and non-team employee records exist | E14: 1. Sign in as manager 2. Open time tracking dashboard 3. Review visible employees and attempt access to non-team details | F14: Manager with scoped team membership | G14: Manager sees only authorized team data and cannot view unrelated employee time entries | H14: High | I14: Security | J14: Later | K14: Not Run | L14: Req: EMP-002 | Risk: privacy breach

Sheet Customers_CRM
A1: Customers and CRM Test Cases
A2: Update the Status column during execution. Summary KPIs and counts refresh automatically.
A4: TC_ID | B4: Module | C4: Scenario | D4: Preconditions | E4: Steps | F4: Test Data | G4: Expected Result | H4: Priority | I4: Type | J4: Automation Candidate | K4: Status | L4: Notes
A5: TC-CRM-001 | B5: Customers & CRM | C5: Verify company can be created with valid required fields | D5: User has CRM create permission | E5: 1. Open company creation 2. Enter required company fields 3. Save the company | F5: Valid company data | G5: Company saves successfully and is searchable in CRM | H5: High | I5: Positive | J5: Yes | K5: Not Run | L5: Req: CRM-001 | Risk: customer master setup
A6: TC-CRM-002 | B6: Customers & CRM | C6: Verify duplicate company handling follows configured rule | D6: A company with same unique identifier exists | E6: 1. Attempt to create a company with duplicate unique identifier 2. Save the record | F6: Existing company identifier | G6: System blocks or flags duplicate according to business rule and avoids ambiguous records | H6: High | I6: Negative | J6: Yes | K6: Not Run | L6: Req: CRM-002 | Risk: duplicate billing entity
A7: TC-CRM-003 | B7: Customers & CRM | C7: Verify contact can be created and linked to a parent company | D7: Parent company exists | E7: 1. Open contact creation from company context 2. Enter valid contact details 3. Save contact | F7: Valid contact data | G7: Contact is saved and linked to the correct parent company | H7: High | I7: Positive | J7: Yes | K7: Not Run | L7: Req: CRM-003 | Risk: orphaned contact records
A8: TC-CRM-004 | B8: Customers & CRM | C8: Verify required contact fields and format validations are enforced | D8: Contact creation page is open | E8: 1. Leave required fields blank or enter invalid email/phone 2. Attempt to save | F8: Blank required values and invalid formats | G8: Validation messages appear and no invalid contact is created | H8: High | I8: Negative | J8: Yes | K8: Not Run | L8: Req: CRM-004 | Risk: bad contact data
A9: TC-CRM-005 | B9: Customers & CRM | C9: Verify company notes and flags are visible across CRM and order entry | D9: Company with notes/flags exists | E9: 1. Open company record and add a note/flag 2. Open related CRM list and order entry page 3. Review surfaced note/flag indicators | F9: Company with internal note and flag | G9: Notes/flags are displayed where intended without leaking private text externally | H9: Medium | I9: Regression | J9: Later | K9: Not Run | L9: Req: CRM-005 | Risk: missed customer handling instructions
A10: TC-CRM-006 | B10: Customers & CRM | C10: Verify contact notes and flags are retained in audit/history views | D10: Existing contact exists | E10: 1. Add or update a contact note/flag 2. Open contact history or audit trail 3. Review change details | F10: Updated contact metadata | G10: History captures the change with user/date context and current CRM view stays accurate | H10: Medium | I10: Regression | J10: Later | K10: Not Run | L10: Req: CRM-006 | Risk: lack of traceability
A11: TC-CRM-007 | B11: Customers & CRM | C11: Verify CRM list filters and search results update accurately | D11: Multiple companies and contacts exist | E11: 1. Apply status, owner, or text filters 2. Review returned CRM records 3. Clear filters and compare counts | F11: Sample CRM dataset | G11: CRM list shows only matching records and counts refresh correctly | H11: Medium | I11: Positive | J11: Yes | K11: Not Run | L11: Req: CRM-007 | Risk: missed follow-up due to bad filtering
A12: TC-CRM-008 | B12: Customers & CRM | C12: Verify portal invitation can only be sent to a valid contact email | D12: Company and contact exist | E12: 1. Open portal invitation flow 2. Select contact with valid email 3. Send invitation 4. Repeat with missing or malformed email | F12: Valid and invalid contact email cases | G12: Invitation is sent only to valid contact email addresses and invalid cases are blocked | H12: High | I12: Negative | J12: Later | K12: Not Run | L12: Req: PORTAL-001 | Risk: failed portal onboarding
A13: TC-CRM-009 | B13: Customers & CRM | C13: Verify invitation resend or token expiry behavior is controlled | D13: Portal invitation has already been sent | E13: 1. Attempt to use an expired invitation link if available 2. Trigger resend from CRM 3. Open the latest link | F13: Expired invite and resent token | G13: Expired token is rejected and the newest valid invitation works as expected | H13: High | I13: Security | J13: Later | K13: Not Run | L13: Req: PORTAL-002 | Risk: account takeover via stale link
A14: TC-CRM-010 | B14: Customers & CRM | C14: Verify merge or de-duplication preserves linked order history | D14: Two duplicate customer records exist and one has transactions | E14: 1. Start duplicate merge flow 2. Merge duplicate into surviving record 3. Review existing orders and payments | F14: Duplicate company/contact pair | G14: Historical orders, payments, and notes remain linked to the surviving record without data loss | H14: Critical | I14: Regression | J14: Later | K14: Not Run | L14: Req: CRM-008 | Risk: broken customer history

Sheet Sales_Orders
A1: Sales, Estimates, and Orders Test Cases
A2: Update the Status column during execution. Summary KPIs and counts refresh automatically.
A4: TC_ID | B4: Module | C4: Scenario | D4: Preconditions | E4: Steps | F4: Test Data | G4: Expected Result | H4: Priority | I4: Type | J4: Automation Candidate | K4: Status | L4: Notes
A5: TC-SAL-001 | B5: Sales & Orders | C5: Verify estimate can be created with multiple line items, fees, and tax | D5: Customer and sellable items exist | E5: 1. Create a new estimate 2. Add multiple line items and an order-level fee 3. Apply tax and save | F5: Sample customer, items, fee, and tax group | G5: Estimate saves with accurate subtotal, tax, and total | H5: Critical | I5: Positive | J5: Yes | K5: Not Run | L5: Req: SALES-001 | Risk: inaccurate quote totals
A6: TC-SAL-002 | B6: Sales & Orders | C6: Verify estimate-to-order conversion preserves customer, item, price, and tax data | D6: Approved estimate exists | E6: 1. Open an approved estimate 2. Convert estimate to order 3. Compare order values to source estimate | F6: Saved estimate with multiple lines | G6: Order is created with all expected customer, item, pricing, tax, and notes preserved | H6: Critical | I6: Regression | J6: Yes | K6: Not Run | L6: Req: SALES-002 | Risk: data loss during conversion
A7: TC-SAL-003 | B7: Sales & Orders | C7: Verify a direct order can be created without starting from an estimate | D7: User has order-create permission | E7: 1. Open new order 2. Enter required customer and line item data 3. Save the order | F7: Valid order data | G7: Order saves successfully with generated identifier and correct initial status | H7: High | I7: Positive | J7: Yes | K7: Not Run | L7: Req: SALES-003 | Risk: blocked direct-order workflow
A8: TC-SAL-004 | B8: Sales & Orders | C8: Verify invalid status transition is blocked and valid transition is logged | D8: Order exists in a controlled status flow | E8: 1. Attempt a disallowed status jump 2. Then perform an allowed next status change 3. Open history/audit trail | F8: Order with configured statuses | G8: Disallowed transition is blocked and allowed transition is recorded in order history | H8: Critical | I8: Negative | J8: Yes | K8: Not Run | L8: Req: SALES-004 | Risk: workflow bypass
A9: TC-SAL-005 | B9: Sales & Orders | C9: Verify board view filters return the correct orders by owner, status, and location | D9: Board setup and sample orders exist | E9: 1. Open board view 2. Apply owner, status, and location filters 3. Review visible cards and counts | F9: Orders across owners, statuses, and locations | G9: Board displays only matching orders and filter counts are accurate | H9: Medium | I9: Positive | J9: Yes | K9: Not Run | L9: Req: SALES-005 | Risk: wrong work queue visibility
A10: TC-SAL-006 | B10: Sales & Orders | C10: Verify clipboard copy/paste duplicates intended line items without stale references | D10: Order with line items exists | E10: 1. Copy a line item using clipboard feature 2. Paste into same or new estimate/order 3. Review price, quantity, and product reference | F10: Order with standard items | G10: Copied item duplicates correctly and no stale hidden references are carried over | H10: High | I10: Regression | J10: Later | K10: Not Run | L10: Req: SALES-006 | Risk: duplicated incorrect data
A11: TC-SAL-007 | B11: Sales & Orders | C11: Verify recurring template creates the next draft transaction using configured cadence | D11: Recurring template exists | E11: 1. Run or wait for recurring template generation 2. Open the generated draft 3. Compare cadence-driven dates and copied details | F11: Recurring template with start date and interval | G11: New draft transaction is created once with correct copied details and schedule | H11: High | I11: Integration | J11: Later | K11: Not Run | L11: Req: SALES-007 | Risk: duplicate recurring orders
A12: TC-SAL-008 | B12: Sales & Orders | C12: Verify multi-quantity estimates recalculate line extensions and totals correctly | D12: Estimate screen supports multi-quantity pricing | E12: 1. Create an estimate with quantity brackets or multi-quantity entries 2. Review line extension and total recalculation 3. Save and reopen | F12: Multiple quantities and price points | G12: All line extensions and estimate totals calculate correctly and persist after save | H12: High | I12: Boundary | J12: Yes | K12: Not Run | L12: Req: SALES-008 | Risk: quantity pricing errors
A13: TC-SAL-009 | B13: Sales & Orders | C13: Verify overpayment converts to in-store credit according to business rule | D13: Order with small remaining balance exists | E13: 1. Enter a payment above remaining balance where allowed 2. Review resulting balance and credit record | F13: Order with intentional overpayment scenario | G13: Overpayment is handled according to configured rule and resulting store credit is accurate | H13: Critical | I13: Boundary | J13: Later | K13: Not Run | L13: Req: SALES-009 | Risk: unapplied cash or customer credit mismatch
A14: TC-SAL-010 | B14: Sales & Orders | C14: Verify order and line-item fees update subtotal, tax, and grand total correctly | D14: Order exists and fee setup is available | E14: 1. Apply a taxable line-item fee 2. Apply an order-level fee 3. Review totals before and after save | F14: Taxable and non-taxable fee setup | G14: Fees are included in the correct calculation layers and totals remain consistent | H14: Critical | I14: Regression | J14: Yes | K14: Not Run | L14: Req: SALES-010 | Risk: miscalculated fees
A15: TC-SAL-011 | B15: Sales & Orders | C15: Verify full unlock is restricted and creates clear history when used | D15: Invoiced or locked order exists | E15: 1. Attempt full unlock as unauthorized user 2. Repeat as authorized user 3. Review audit/history | F15: Locked order and two user roles | G15: Unauthorized access is blocked; authorized unlock is recorded with traceable history | H15: Critical | I15: Security | J15: Later | K15: Not Run | L15: Req: SALES-011 | Risk: untracked financial edits
A16: TC-SAL-012 | B16: Sales & Orders | C16: Verify destination fields and validation rules behave correctly for delivery scenarios | D16: Order form supports destination handling | E16: 1. Create an order requiring destination details 2. Leave a required destination field blank 3. Correct the data and save | F16: Delivery destination sample data | G16: Required destination fields validate correctly and saved order shows the right delivery details | H16: Medium | I16: Negative | J16: Later | K16: Not Run | L16: Req: SALES-012 | Risk: fulfillment errors

Sheet Components_Pricing
A1: Components and Pricing Test Cases
A2: Update the Status column during execution. Summary KPIs and counts refresh automatically.
A4: TC_ID | B4: Module | C4: Scenario | D4: Preconditions | E4: Steps | F4: Test Data | G4: Expected Result | H4: Priority | I4: Type | J4: Automation Candidate | K4: Status | L4: Notes
A5: TC-CMP-001 | B5: Components & Pricing | C5: Verify material can be created with required cost, unit, and category | D5: Component admin user is logged in | E5: 1. Open material creation 2. Enter required master data and cost 3. Save the material | F5: Valid material master data | G5: Material saves successfully and is available for use in pricing structures | H5: High | I5: Positive | J5: Yes | K5: Not Run | L5: Req: CMP-001 | Risk: incomplete component master
A6: TC-CMP-002 | B6: Components & Pricing | C6: Verify cloned material or labor creates an independent editable record | D6: Existing material or labor exists | E6: 1. Clone a material or labor record 2. Modify the clone 3. Review original record | F6: Existing component to clone | G6: Clone is created with copied baseline values and edits do not alter the original | H6: Medium | I6: Regression | J6: Later | K6: Not Run | L6: Req: CMP-002 | Risk: accidental master data overwrite
A7: TC-CMP-003 | B7: Components & Pricing | C7: Verify labor cost worksheet rolls up rate, burden, and total correctly | D7: Labor worksheet is enabled | E7: 1. Enter base rate and burden inputs 2. Review calculated labor total 3. Save the labor record | F7: Labor inputs for rate and burden | G7: Worksheet calculations are correct and saved labor cost matches the worksheet result | H7: High | I7: Positive | J7: Yes | K7: Not Run | L7: Req: CMP-003 | Risk: understated labor cost
A8: TC-CMP-004 | B8: Components & Pricing | C8: Verify machine cost configuration affects priced output as expected | D8: Machine component exists or can be created | E8: 1. Create or update a machine hourly cost 2. Use the machine in a priced item or assembly 3. Review priced result | F8: Machine rate and runtime assumptions | G8: Machine cost is incorporated into priced output using configured assumptions | H8: High | I8: Integration | J8: Later | K8: Not Run | L8: Req: CMP-004 | Risk: missing machine cost
A9: TC-CMP-005 | B9: Components & Pricing | C9: Verify cost-plus pricing calculates sell price from cost and markup settings | D9: Pricing engine supports cost-plus method | E9: 1. Configure cost-plus pricing inputs 2. Create or update a priced item 3. Review generated sell price | F9: Known cost and markup inputs | G9: Sell price matches expected cost-plus formula and rounding rule | H9: Critical | I9: Positive | J9: Yes | K9: Not Run | L9: Req: PRICE-001 | Risk: margin leakage
A10: TC-CMP-006 | B10: Components & Pricing | C10: Verify market-based or tier pricing overrides base cost-driven output where configured | D10: Pricing tiers or market-based rules exist | E10: 1. Assign a market or tier rule 2. Price the same item under the rule 3. Compare to cost-based result | F10: Tier or market pricing rule | G10: Configured pricing rule supersedes base cost result according to priority rules | H10: Critical | I10: Regression | J10: Later | K10: Not Run | L10: Req: PRICE-002 | Risk: wrong customer price
A11: TC-CMP-007 | B11: Components & Pricing | C11: Verify materials with variants select the correct cost and identifier | D11: Variant-enabled material exists | E11: 1. Create or select a material with variants 2. Choose different variants in pricing flow 3. Review cost and identifier mapping | F11: Variant material dataset | G11: Selected variant drives the correct cost, SKU/identifier, and description | H11: High | I11: Boundary | J11: Later | K11: Not Run | L11: Req: CMP-005 | Risk: wrong variant costing
A12: TC-CMP-008 | B12: Components & Pricing | C12: Verify bill of materials total includes material, labor, and machine contributors | D12: Assembly or BOM feature is enabled | E12: 1. Create or open a BOM with material, labor, and machine inputs 2. Review total cost and priced output | F12: Sample assembly with multiple component types | G12: BOM total includes all configured component contributors without duplication | H12: Critical | I12: Integration | J12: Later | K12: Not Run | L12: Req: CMP-006 | Risk: incomplete assembly cost
A13: TC-CMP-009 | B13: Components & Pricing | C13: Verify deletion of a component in active use is restricted or safely handled | D13: Component is referenced by active items | E13: 1. Attempt to delete a referenced component 2. Review warning and resulting references | F13: Component linked to active items | G13: System blocks unsafe deletion or handles dependency cleanup per business rule | H13: High | I13: Negative | J13: Later | K13: Not Run | L13: Req: CMP-007 | Risk: broken pricing references

Sheet Financial_Config
A1: Financial Setup Test Cases
A2: Update the Status column during execution. Summary KPIs and counts refresh automatically.
A4: TC_ID | B4: Module | C4: Scenario | D4: Preconditions | E4: Steps | F4: Test Data | G4: Expected Result | H4: Priority | I4: Type | J4: Automation Candidate | K4: Status | L4: Notes
A5: TC-FIN-001 | B5: Financial Setup | C5: Verify payment terms can be created and applied as default on new transactions | D5: Finance admin user is logged in | E5: 1. Create a new payment term such as Net 30 2. Mark it as default if allowed 3. Create a new estimate or order | F5: Valid payment term configuration | G5: New transactions inherit the configured default payment term | H5: High | I5: Positive | J5: Yes | K5: Not Run | L5: Req: FIN-001 | Risk: inconsistent payment expectations
A6: TC-FIN-002 | B6: Financial Setup | C6: Verify invalid payment term values such as negative days are rejected | D6: Payment terms page is open | E6: 1. Create or edit a payment term with negative days or invalid offset 2. Attempt to save | F6: Negative or invalid term values | G6: Invalid configuration is rejected with clear validation | H6: Medium | I6: Negative | J6: Yes | K6: Not Run | L6: Req: FIN-002 | Risk: invalid due dates
A7: TC-FIN-003 | B7: Financial Setup | C7: Verify chart of accounts entry requires mandatory fields and unique mapping keys | D7: COA page is available | E7: 1. Create an account with missing required fields 2. Correct fields and save 3. Attempt duplicate unique code if supported | F7: Valid and invalid GL account data | G7: Only valid chart of accounts entries save and duplicates are prevented | H7: High | I7: Negative | J7: Yes | K7: Not Run | L7: Req: FIN-003 | Risk: bad GL master data
A8: TC-FIN-004 | B8: Financial Setup | C8: Verify default GL accounts are required before accounting export or sync | D8: Accounting sync is configured in QA | E8: 1. Remove or blank a required default GL mapping 2. Attempt accounting export or sync 3. Restore mapping and retry | F8: Missing GL mapping scenario | G8: System blocks export/sync until required default GL mapping is completed | H8: Critical | I8: Integration | J8: Later | K8: Not Run | L8: Req: FIN-004 | Risk: unpostable accounting data
A9: TC-FIN-005 | B9: Financial Setup | C9: Verify taxability codes, tax items, and tax groups calculate expected tax | D9: Tax master data exists | E9: 1. Create a taxable transaction with known rates 2. Apply different taxability codes or groups 3. Review calculated tax | F9: Known tax scenarios | G9: Tax amount matches expected calculation for the applied taxability rule | H9: Critical | I9: Positive | J9: Yes | K9: Not Run | L9: Req: FIN-005 | Risk: tax under/over collection
A10: TC-FIN-006 | B10: Financial Setup | C10: Verify financial rounding is applied consistently at line, subtotal, tax, and total levels | D10: Rounding rules are enabled | E10: 1. Create a transaction with fractional amounts 2. Review line totals, tax, and final total 3. Compare to expected rounded result | F10: Amounts designed to exercise rounding | G10: Rounding behavior is consistent with configured rule across all calculation layers | H10: Critical | I10: Boundary | J10: Yes | K10: Not Run | L10: Req: FIN-006 | Risk: penny mismatches
A11: TC-FIN-007 | B11: Financial Setup | C11: Verify credit line limits block release or payment scenarios according to rule | D11: Customer with credit line exists | E11: 1. Create transaction that would exceed available credit 2. Attempt to proceed to restricted step | F11: Customer near credit limit | G11: System enforces credit limit rule and shows actionable guidance | H11: High | I11: Negative | J11: Later | K11: Not Run | L11: Req: FIN-007 | Risk: unauthorized credit exposure
A12: TC-FIN-008 | B12: Financial Setup | C12: Verify unlocking invoiced or closed transactions is restricted and auditable | D12: Closed or invoiced transaction exists | E12: 1. Attempt unlock with unauthorized role 2. Repeat with authorized role 3. Review audit trail and downstream flags | F12: Closed financial transaction and two user roles | G12: Only authorized users can unlock and the action is traceable | H12: Critical | I12: Security | J12: Later | K12: Not Run | L12: Req: FIN-008 | Risk: financial integrity breach
A13: TC-FIN-009 | B13: Financial Setup | C13: Verify pricing mode changes recalculate quote output without corrupting stored cost data | D13: Pricing methods are available | E13: 1. Create a priced estimate under one pricing mode 2. Switch pricing mode for the same scenario 3. Review recalculated price and stored cost basis | F13: Known cost and pricing setup | G13: Displayed quote price updates according to new pricing mode while source cost data remains intact | H13: High | I13: Regression | J13: Later | K13: Not Run | L13: Req: FIN-009 | Risk: price/cost data corruption
A14: TC-FIN-010 | B14: Financial Setup | C14: Verify automatic reconciliation setting changes downstream reconciliation workflow behavior | D14: Automatic reconciliation option is available | E14: 1. Enable or disable automatic reconciliation in QA 2. Process a small payment batch 3. Open reconciliation workflow | F14: Same payment batch under both settings | G14: Reconciliation workflow behavior matches configuration without skipping required controls | H14: High | I14: Integration | J14: Later | K14: Not Run | L14: Req: FIN-010 | Risk: unexpected auto-close behavior

Sheet Payments_Recon
A1: Payments and Reconciliation Test Cases
A2: Update the Status column during execution. Summary KPIs and counts refresh automatically.
A4: TC_ID | B4: Module | C4: Scenario | D4: Preconditions | E4: Steps | F4: Test Data | G4: Expected Result | H4: Priority | I4: Type | J4: Automation Candidate | K4: Status | L4: Notes
A5: TC-PAY-001 | B5: Payments & Reconciliation | C5: Verify enabling or disabling a built-in payment method changes payment screen availability | D5: Finance setup access is available | E5: 1. Disable a built-in payment method 2. Open payment entry 3. Re-enable the method and retest | F5: Built-in payment method configuration | G5: Disabled method is hidden or inactive; re-enabled method is available immediately or after refresh as designed | H5: High | I5: Regression | J5: Yes | K5: Not Run | L5: Req: PAY-001 | Risk: wrong payment options
A6: TC-PAY-002 | B6: Payments & Reconciliation | C6: Verify a custom payment method posts to the configured deposit account | D6: Custom payment method setup is available | E6: 1. Create or edit a custom payment method with deposit account mapping 2. Take a payment using the method 3. Review stored payment details | F6: Custom payment method and deposit account | G6: Payment stores the correct payment method and deposit account mapping | H6: Critical | I6: Positive | J6: Yes | K6: Not Run | L6: Req: PAY-002 | Risk: wrong cash account posting
A7: TC-PAY-003 | B7: Payments & Reconciliation | C7: Verify an integrated card payment approval creates a payment and reduces order balance | D7: Integrated gateway is online in QA or mocked | E7: 1. Open an unpaid order 2. Take an integrated card payment 3. Review payment history and remaining balance | F7: Valid integrated payment credentials and test card | G7: Approved payment is recorded once and order balance decreases by the captured amount | H7: Critical | I7: Integration | J7: Yes | K7: Not Run | L7: Req: PAY-003 | Risk: approved payment not posted
A8: TC-PAY-004 | B8: Payments & Reconciliation | C8: Verify manual non-integrated card entry requires reference or audit note where configured | D8: Non-integrated card method is enabled | E8: 1. Start a manual card payment 2. Leave required reference blank if applicable 3. Attempt to save | F8: Manual card payment data | G8: Validation enforces required reference/audit fields before payment can be saved | H8: High | I8: Negative | J8: Later | K8: Not Run | L8: Req: PAY-004 | Risk: unverifiable manual payments
A9: TC-PAY-005 | B9: Payments & Reconciliation | C9: Verify partial payment updates remaining balance accurately | D9: Unpaid order with known balance exists | E9: 1. Take a partial payment 2. Review remaining balance and payment history | F9: Known order balance and partial amount | G9: Remaining balance equals original balance minus partial payment and payment history shows the transaction | H9: Critical | I9: Positive | J9: Yes | K9: Not Run | L9: Req: PAY-005 | Risk: incorrect AR balance
A10: TC-PAY-006 | B10: Payments & Reconciliation | C10: Verify payment amount above remaining balance is blocked or handled per credit rule | D10: Order with small remaining balance exists | E10: 1. Attempt payment above remaining balance 2. Review resulting behavior and messages | F10: Amount greater than remaining balance | G10: System blocks the payment or creates controlled store credit according to configured rule | H10: Critical | I10: Boundary | J10: Later | K10: Not Run | L10: Req: PAY-006 | Risk: unapplied over-collection
A11: TC-PAY-007 | B11: Payments & Reconciliation | C11: Verify customer portal payment is available only when integrated payments are enabled | D11: Portal access is configured for a customer | E11: 1. Disable integrated payment provider 2. Open unpaid order in portal 3. Enable provider and retest | F11: Portal-enabled customer and unpaid order | G11: Portal payment call-to-action follows integration availability setting exactly | H11: Critical | I11: Integration | J11: Later | K11: Not Run | L11: Req: PAY-007 | Risk: broken customer payment experience
A12: TC-PAY-008 | B12: Payments & Reconciliation | C12: Verify full refund updates payment status, order balance, and audit trail | D12: Completed payment exists and is refundable | E12: 1. Open payment or order 2. Initiate full refund 3. Review balances and payment status | F12: Completed payment eligible for refund | G12: Refund is created once, payment status updates appropriately, and balances remain consistent | H12: Critical | I12: Regression | J12: Yes | K12: Not Run | L12: Req: PAY-008 | Risk: refund mismatch
A13: TC-PAY-009 | B13: Payments & Reconciliation | C13: Verify partial refund cannot exceed captured amount or remaining refundable balance | D13: Completed payment exists | E13: 1. Attempt a partial refund above allowed amount 2. Then refund a valid partial amount | F13: Completed payment and excessive refund amount | G13: Excessive refund is blocked and valid partial refund updates refundable balance correctly | H13: Critical | I13: Negative | J13: Yes | K13: Not Run | L13: Req: PAY-009 | Risk: excess cash outflow
A14: TC-PAY-010 | B14: Payments & Reconciliation | C14: Verify a multi-order payment allocates exact amounts across selected orders | D14: Customer has multiple open orders | E14: 1. Start multi-order payment 2. Allocate different amounts across orders 3. Save payment and review each order | F14: Customer with two or more open orders | G14: Allocated amounts post to the intended orders and each remaining balance is correct | H14: Critical | I14: Integration | J14: Later | K14: Not Run | L14: Req: PAY-010 | Risk: misapplied cash
A15: TC-PAY-011 | B15: Payments & Reconciliation | C15: Verify reconciliation preview groups transactions by correct location, date, and payment method | D15: Unreconciled payments exist across locations | E15: 1. Open reconciliation preview 2. Filter by location or period 3. Review grouped totals | F15: Sample payments across locations and methods | G15: Preview shows the correct unreconciled transactions and grouped totals for the selected scope | H15: Critical | I15: Positive | J15: Yes | K15: Not Run | L15: Req: REC-001 | Risk: wrong reconciliation bucket
... A18: TC-PAY-014 | B18: Payments & Reconciliation | C18: Verify chargeback or returned payment creates an exception workflow without deleting history | D18: Completed payment exists and exception scenario can be simulated | E18: 1. Simulate chargeback or returned payment event 2. Review payment history, exception queue, and balances | F18: Chargeback/return simulation | G18: Original payment history is retained and exception state is recorded with correct financial impact | H18: High | I18: Integration | J18: Later | K18: Not Run | L18: Req: PAY-011 | Risk: silent revenue reversal

Sheet Integrations_Reports
A1: Integrations and Reporting Test Cases
A2: Update the Status column during execution. Summary KPIs and counts refresh automatically.
A4: TC_ID | B4: Module | C4: Scenario | D4: Preconditions | E4: Steps | F4: Test Data | G4: Expected Result | H4: Priority | I4: Type | J4: Automation Candidate | K4: Status | L4: Notes
A5: TC-INT-001 | B5: Integrations & Reporting | C5: Verify gateway connectivity test succeeds with valid credentials | D5: Integration settings page is available | E5: 1. Enter valid gateway credentials or sandbox keys 2. Run connectivity test | F5: Valid sandbox credentials | G5: Connectivity test succeeds and integration status is shown as healthy or online | H5: High | I5: Integration | J5: Yes | K5: Not Run | L5: Req: INT-001 | Risk: false positive gateway status
A6: TC-INT-002 | B6: Integrations & Reporting | C6: Verify declined or timed-out gateway response does not create duplicate payment records | D6: Gateway decline or timeout can be simulated | E6: 1. Initiate an integrated payment 2. Simulate timeout or decline 3. Retry once if allowed and review payment history | F6: Decline/timeout payment scenario | G6: No duplicate payment is created and user sees clear retry-safe messaging | H6: Critical | I6: Integration | J6: Yes | K6: Not Run | L6: Req: INT-002 | Risk: duplicate charge
A7: TC-INT-003 | B7: Integrations & Reporting | C7: Verify accounting summary sync exports balanced totals | D7: Accounting sandbox is connected | E7: 1. Prepare a batch of transactions 2. Run summary sync/export 3. Review exported totals in outbound payload or target system | F7: Known batch totals | G7: Exported journal or summary data is balanced and matches source totals | H7: Critical | I7: Data | J7: Later | K7: Not Run | L7: Req: INT-003 | Risk: unbalanced accounting export
A8: TC-INT-004 | B8: Integrations & Reporting | C8: Verify accounting detail sync preserves customer, order, and payment dimensions | D8: Detail sync is enabled in QA | E8: 1. Create sample transactions with known customer/order/payment data 2. Run detail sync 3. Review target-side detail records | F8: Known transaction set | G8: Target accounting detail includes the correct dimensional fields and mapped accounts | H8: Critical | I8: Integration | J8: Later | K8: Not Run | L8: Req: INT-004 | Risk: lost reporting dimensions
A9: TC-INT-005 | B9: Integrations & Reporting | C9: Verify external tax lookup failure falls back or errors gracefully | D9: External tax lookup is configured and can be disabled | E9: 1. Start a taxable transaction 2. Simulate tax service outage 3. Review system behavior | F9: Tax service unavailable scenario | G9: System follows defined fallback or blocking behavior without silently miscalculating tax | H9: High | I9: Integration | J9: Later | K9: Not Run | L9: Req: INT-005 | Risk: silent tax failure
A10: TC-INT-006 | B10: Integrations & Reporting | C10: Verify email or calendar integration creates activities only once per event | D10: Email/calendar integration is connected in QA | E10: 1. Trigger an activity that should sync 2. Review generated email/calendar activity 3. Repeat refresh or sync job | F10: Single event eligible for sync | G10: Only one corresponding external activity is created and duplicate sync is avoided | H10: Medium | I10: Integration | J10: Later | K10: Not Run | L10: Req: INT-006 | Risk: duplicate external events
A11: TC-INT-007 | B11: Integrations & Reporting | C11: Verify API rejects unauthorized requests and records access attempt | D11: API endpoint and logs are available | E11: 1. Call an API with missing or invalid authorization 2. Review response and audit logs | F11: Unauthorized API request | G11: Request is rejected with appropriate status and access attempt is traceable | H11: Critical | I11: Security | J11: Yes | K11: Not Run | L11: Req: INT-007 | Risk: unauthorized data access
A12: TC-INT-008 | B12: Integrations & Reporting | C12: Verify report filters and drill-down totals match the underlying transaction list | D12: Reporting module has sample data | E12: 1. Open a financial or operational report 2. Apply date/location/method filters 3. Drill down to underlying transactions | F12: Known dataset with filters | G12: Filtered totals match the drilled-down transactions exactly | H12: Critical | I12: Data | J12: Yes | K12: Not Run | L12: Req: REP-001 | Risk: misleading management reporting
A13: TC-INT-009 | B13: Integrations & Reporting | C13: Verify generated documents populate merge fields with correct sanitized data | D13: Document template exists | E13: 1. Generate a customer-facing document 2. Review populated merge fields and totals | F13: Sample order and template | G13: Document shows the correct sanitized customer, order, and total data without blank required merge fields | H13: High | I13: Regression | J13: Later | K13: Not Run | L13: Req: DOC-001 | Risk: incorrect customer document
A14: TC-INT-010 | B14: Integrations & Reporting | C14: Verify report or document export to PDF/CSV preserves totals and formats | D14: Export-capable report exists | E14: 1. Run a report or generate a document 2. Export to supported format 3. Open exported file and review totals/format | F14: Known report totals | G14: Exported file preserves totals, date formats, and key labels accurately | H14: High | I14: Regression | J14: Later | K14: Not Run | L14: Req: REP-002 | Risk: corrupted exported evidence
A15: TC-INT-011 | B15: Integrations & Reporting | C15: Verify retry after temporary sync failure does not duplicate exported records | D15: A sync job can be retried in QA | E15: 1. Cause a temporary failure for outbound sync 2. Retry the same job after recovery 3. Review target system and source status | F15: Temporary failure and retry scenario | G15: Retried sync completes once and does not create duplicate target records | H15: Critical | I15: Integration | J15: Later | K15: Not Run | L15: Req: INT-008 | Risk: duplicate accounting or messaging records

Sheet End_to_End
A1: End-to-End Test Cases
A2: Update the Status column during execution. Summary KPIs and counts refresh automatically.
A4: TC_ID | B4: Module | C4: Scenario | D4: Preconditions | E4: Steps | F4: Test Data | G4: Expected Result | H4: Priority | I4: Type | J4: Automation Candidate | K4: Status | L4: Notes
A5: TC-E2E-001 | B5: End-to-End | C5: Verify full order-to-cash flow from company setup through reconciliation close | D5: Required master data, payment methods, and user access are configured | E5: 1. Create a company and contact 2. Create an estimate with taxed line items 3. Convert estimate to order 4. Take an integrated partial payment 5. Take final payment 6. Open reconciliation and close balanced batch | F5: New customer, order, and two payments | G5: Customer, sales, payment, and reconciliation records stay linked and financially consistent end to end | H5: Critical | I5: Regression | J5: Later | K5: Not Run | L5: Scenario: primary happy path
A6: TC-E2E-002 | B6: End-to-End | C6: Verify customer portal invitation to successful portal payment updates internal records | D6: Portal-enabled contact and unpaid order exist | E6: 1. Send portal invitation 2. Open portal as customer 3. Pay the order using enabled integrated payments 4. Review internal payment and balance | F6: Portal-enabled customer and unpaid order | G6: Portal payment succeeds and internal order/payment history updates without manual intervention | H6: Critical | I6: Integration | J6: Later | K6: Not Run | L6: Scenario: external customer payment
A7: TC-E2E-003 | B7: End-to-End | C7: Verify partial payment followed by partial refund and reconciliation exception handling remains balanced | D7: Order, payment, and refund permissions exist | E7: 1. Create order and take partial payment 2. Issue a valid partial refund 3. Open reconciliation or exception workflow 4. Review remaining balance and refund history | F7: Known order, payment, and refund amounts | G7: Balances, refund history, and reconciliation status remain logically consistent across the lifecycle | H7: Critical | I7: Regression | J7: Later | K7: Not Run | L7: Scenario: money movement reversal
A8: TC-E2E-004 | B8: End-to-End | C8: Verify multi-location transaction posts and reports against the correct location throughout the lifecycle | D8: Two locations exist with separate activity | E8: 1. Create and pay an order under location A 2. Create a second order under location B 3. Run location-filtered reports and reconciliation previews | F8: Location-specific orders and payments | G8: Each transaction remains attached to the correct location in operational and financial views | H8: Critical | I8: Data | J8: Later | K8: Not Run | L8: Scenario: multi-location integrity
A9: TC-E2E-005 | B9: End-to-End | C9: Verify BOM-based pricing flows from component setup into estimate and final order total | D9: Components, assembly, and pricing rules are configured | E9: 1. Create or update a BOM-driven priced item 2. Add the item to an estimate 3. Convert to order and review totals | F9: Known BOM-driven product | G9: Component-driven pricing is reflected consistently from pricing engine through final transaction | H9: Critical | I9: Integration | J9: Later | K9: Not Run | L9: Scenario: costing to selling price
A10: TC-E2E-006 | B10: End-to-End | C10: Verify locked invoiced order change control preserves auditability and reporting integrity | D10: Invoiced or financially posted order exists | E10: 1. Attempt edit as unauthorized user 2. Unlock/edit as authorized user if allowed 3. Review history and reporting impact | F10: Locked order with two user roles | G10: Change control is enforced and any permitted edit remains fully traceable without silent report drift | H10: Critical | I10: Security | J10: Later | K10: Not Run | L10: Scenario: post-invoice governance
A11: TC-E2E-007 | B11: End-to-End | C11: Verify accounting sync after daily close exports only eligible balanced data | D11: Accounting sandbox is connected and a closed batch exists | E11: 1. Prepare balanced and unbalanced transaction groups 2. Close only the balanced group 3. Run accounting sync 4. Review exported content | F11: Balanced and unbalanced batches | G11: Only eligible balanced data is exported and unbalanced data remains excluded pending correction | H11: Critical | I11: Integration | J11: Later | K11: Not Run | L11: Scenario: controlled accounting handoff
A12: TC-E2E-008 | B12: End-to-End | C12: Verify restricted user can manage CRM and sales tasks but cannot access protected financial setup | D12: Role matrix is configured | E12: 1. Sign in as restricted operational user 2. Create customer and order records 3. Attempt access to financial setup and reconciliation pages | F12: Operational user role | G12: Operational workflows work while protected financial actions stay blocked throughout the session | H12: High | I12: Security | J12: Yes | K12: Not Run | L12: Scenario: separation of duties
